nospamplus/__init__.py
nospamplus/class_types.py
nospamplus/connect.py
nospamplus-5.0.dist-info/LICENSE
nospamplus-5.0.dist-info/METADATA
nospamplus-5.0.dist-info/WHEEL
nospamplus-5.0.dist-info/top_level.txt
nospamplus-5.0.dist-info/RECORD
