Metadata-Version: 2.1
Name: nospamplus
Version: 5.0
Summary: A Python Wrapper For Nospamplus Api
Home-page: http://nospamplus.cf
Author: Leo
Author-email: dev@nospamplus.cf
License: License :: OSI Approved :: GNU Lesser General Public License v3 (LGPLv3)
Platform: UNKNOWN
Classifier: Programming Language :: Python :: 3
Classifier: Operating System :: OS Independent
Requires-Python: >=3.6
Requires-Dist: requests (>=2.22.0)
